psx_syntax/__init__.py
psx_syntax/packed.py
tests/__init__.py
tests/test_component.py
tests/test_element.py
tests/test_translate.py
psx_syntax-0.0.2.dist-info/LICENCE
psx_syntax-0.0.2.dist-info/METADATA
psx_syntax-0.0.2.dist-info/WHEEL
psx_syntax-0.0.2.dist-info/top_level.txt
psx_syntax-0.0.2.dist-info/RECORD
